clickuz/__init__.py
clickuz/admin.py
clickuz/apps.py
clickuz/click_authorization.py
clickuz/clickuz.py
clickuz/models.py
clickuz/serializer.py
clickuz/status.py
clickuz/tests.py
clickuz/views.py
clickuz/migrations/0001_initial.py
clickuz/migrations/__init__.py
ClickUz-0.3.dist-info/LICENSE
ClickUz-0.3.dist-info/METADATA
ClickUz-0.3.dist-info/WHEEL
ClickUz-0.3.dist-info/top_level.txt
ClickUz-0.3.dist-info/RECORD
